german_holidays/german_holidays.py
german_holidays/state_codes.py
german_holidays/__init__.py
germanholidays-0.1.0.dist-info/WHEEL
germanholidays-0.1.0.dist-info/RECORD
germanholidays-0.1.0.dist-info/DESCRIPTION.rst
germanholidays-0.1.0.dist-info/metadata.json
germanholidays-0.1.0.dist-info/top_level.txt
germanholidays-0.1.0.dist-info/METADATA
