Metadata-Version: 2.0
Name: germanholidays
Version: 0.1.0
Summary: German holidays in pandas
Home-page: http://github.com/daviskirk/german-holidays
Author: Davis Kirkendall
Author-email: davis.e.kirkendall@gmail.com
License: MIT
Keywords: pandas,calendar,holidays
Platform: any
Classifier: Programming Language :: Python
Classifier: Programming Language :: Python :: 3
Classifier: Intended Audience :: Developers
Classifier: Development Status :: 4 - Beta
